{
    "Monday": [
      {"id": "8:00", "state": 1, "name": ""},
      {"id": "8:30", "state": 0, "name": ""},
      {"id": "9:00", "state": 0, "name": ""},
      {"id": "9:30", "state": 1, "name": ""},
      {"id": "10:00", "state": 0, "name": ""},
      {"id": "10:30", "state": 0, "name": ""},
      {"id": "11:00", "state": 0, "name": ""},
      {"id": "11:30", "state": 1, "name": ""},
      {"id": "12:00", "state": 0, "name": ""},
      {"id": "12:30", "state": 0, "name": ""},
      {"id": "1:00", "state": 0, "name": ""},
      {"id": "1:30", "state": 0, "name": ""},
      {"id": "2:00", "state": 0, "name": ""},
      {"id": "2:30", "state": 0, "name": ""},      
      {"id": "3:00", "state": 0, "name": ""},
      {"id": "3:30", "state": 0, "name": ""},
      {"id": "4:00", "state": 0, "name": ""},
      {"id": "4:30", "state": 0, "name": ""},      
      {"id": "5:00", "state": 0, "name": ""},
      {"id": "5:30", "state": 0, "name": ""}
    ],
    "Tuesday": [
        {"id": "8:00", "state": 0, "name": ""},
        {"id": "8:30", "state": 0, "name": ""},
        {"id": "9:00", "state": 0, "name": ""},
        {"id": "9:30", "state": 0, "name": ""},
        {"id": "10:00", "state": 0, "name": ""},
        {"id": "10:30", "state": 1, "name": ""},
        {"id": "11:00", "state": 0, "name": ""},
        {"id": "11:30", "state": 0, "name": ""},
        {"id": "12:00", "state": 0, "name": ""},
        {"id": "12:30", "state": 0, "name": ""},
        {"id": "1:00", "state": 0, "name": ""},
        {"id": "1:30", "state": 0, "name": ""},
        {"id": "2:00", "state": 0, "name": ""},
        {"id": "2:30", "state": 0, "name": ""},      
        {"id": "3:00", "state": 0, "name": ""},
        {"id": "3:30", "state": 0, "name": ""},
        {"id": "4:00", "state": 0, "name": ""},
        {"id": "4:30", "state": 0, "name": ""},      
        {"id": "5:00", "state": 0, "name": ""},
        {"id": "5:30", "state": 0, "name": ""}
    ],
    "Wednesday": [
        {"id": "8:00", "state": 0, "name": ""},
        {"id": "8:30", "state": 0, "name": ""},
        {"id": "9:00", "state": 0, "name": ""},
        {"id": "9:30", "state": 0, "name": ""},
        {"id": "10:00", "state": 0, "name": ""},
        {"id": "10:30", "state": 0, "name": ""},
        {"id": "11:00", "state": 0, "name": ""},
        {"id": "11:30", "state": 0, "name": ""},
        {"id": "12:00", "state": 0, "name": ""},
        {"id": "12:30", "state": 0, "name": ""},
        {"id": "1:00", "state": 0, "name": ""},
        {"id": "1:30", "state": 0, "name": ""},
        {"id": "2:00", "state": 0, "name": ""},
        {"id": "2:30", "state": 0, "name": ""},      
        {"id": "3:00", "state": 0, "name": ""},
        {"id": "3:30", "state": 0, "name": ""},
        {"id": "4:00", "state": 0, "name": ""},
        {"id": "4:30", "state": 0, "name": ""},      
        {"id": "5:00", "state": 0, "name": ""},
        {"id": "5:30", "state": 0, "name": ""}
    ],
    "Thursday": [
        {"id": "8:00", "state": 0, "name": ""},
        {"id": "8:30", "state": 0, "name": ""},
        {"id": "9:00", "state": 0, "name": ""},
        {"id": "9:30", "state": 0, "name": ""},
        {"id": "10:00", "state": 0, "name": ""},
        {"id": "10:30", "state": 0, "name": ""},
        {"id": "11:00", "state": 1, "name": ""},
        {"id": "11:30", "state": 0, "name": ""},
        {"id": "12:00", "state": 0, "name": ""},
        {"id": "12:30", "state": 0, "name": ""},
        {"id": "1:00", "state": 0, "name": ""},
        {"id": "1:30", "state": 0, "name": ""},
        {"id": "2:00", "state": 0, "name": ""},
        {"id": "2:30", "state": 0, "name": ""},      
        {"id": "3:00", "state": 0, "name": ""},
        {"id": "3:30", "state": 0, "name": ""},
        {"id": "4:00", "state": 0, "name": ""},
        {"id": "4:30", "state": 0, "name": ""},      
        {"id": "5:00", "state": 0, "name": ""},
        {"id": "5:30", "state": 0, "name": ""}
    ],
    "Friday": [
        {"id": "8:00", "state": 0, "name": ""},
        {"id": "8:30", "state": 0, "name": ""},
        {"id": "9:00", "state": 0, "name": ""},
        {"id": "9:30", "state": 0, "name": ""},
        {"id": "10:00", "state": 0, "name": ""},
        {"id": "10:30", "state": 0, "name": ""},
        {"id": "11:00", "state": 0, "name": ""},
        {"id": "11:30", "state": 0, "name": ""},
        {"id": "12:00", "state": 0, "name": ""},
        {"id": "12:30", "state": 0, "name": ""},
        {"id": "1:00", "state": 0, "name": ""},
        {"id": "1:30", "state": 0, "name": ""},
        {"id": "2:00", "state": 0, "name": ""},
        {"id": "2:30", "state": 0, "name": ""},      
        {"id": "3:00", "state": 0, "name": ""},
        {"id": "3:30", "state": 0, "name": ""},
        {"id": "4:00", "state": 0, "name": ""},
        {"id": "4:30", "state": 0, "name": ""},      
        {"id": "5:00", "state": 0, "name": ""},
        {"id": "5:30", "state": 0, "name": ""}
    ]
  }